LICENSE
README.md
setup.py
kdpy_imagen/__init__.py
kdpy_imagen/cli.py
kdpy_imagen/configs.py
kdpy_imagen/data.py
kdpy_imagen/elucidated_imagen.py
kdpy_imagen/kdpy_imagen.py
kdpy_imagen/t5.py
kdpy_imagen/trainer.py
kdpy_imagen/utils.py
kdpy_imagen/version.py
kdpy_imagen.egg-info/PKG-INFO
kdpy_imagen.egg-info/SOURCES.txt
kdpy_imagen.egg-info/dependency_links.txt
kdpy_imagen.egg-info/entry_points.txt
kdpy_imagen.egg-info/requires.txt
kdpy_imagen.egg-info/top_level.txt
kdpy_imagen/imagen_video/__init__.py
kdpy_imagen/imagen_video/imagen_video.py