Metadata-Version: 2.1
Name: kdpy-imagen
Version: 1.9.3
Summary: Imagen - unprecedented photorealism × deep level of language understanding
Home-page: https://github.com/khanhduy1407/kdpy-imagen
Author: NKDuy
Author-email: kn145660@gmail.com
License: MIT
Keywords: artificial intelligence,deep learning,transformers,text-to-image,denoising-diffusion
Platform: UNKNOWN
Classifier: Development Status :: 4 - Beta
Classifier: Intended Audience :: Developers
Classifier: Topic :: Scientific/Engineering :: Artificial Intelligence
Classifier: License :: OSI Approved :: MIT License
Classifier: Programming Language :: Python :: 3.6
License-File: LICENSE
